C4iosCosmos/README.md
C4iosCosmos/__init__.py
C4iosCosmos/__main__.py
C4iosCosmos/file.epub
C4iosCosmos/index.html
C4iosCosmos/css/__init__.py
C4iosCosmos/css/annotations.css
C4iosCosmos/css/main.css
C4iosCosmos/css/normalize.css
C4iosCosmos/css/popup.css
C4iosCosmos/font/__init__.py
C4iosCosmos/font/fontello.eot
C4iosCosmos/font/fontello.svg
C4iosCosmos/font/fontello.ttf
C4iosCosmos/font/fontello.woff
C4iosCosmos/img/__init__.py
C4iosCosmos/img/annotator-glyph-sprite.png
C4iosCosmos/img/annotator-icon-sprite.png
C4iosCosmos/img/apple-touch-icon.png
C4iosCosmos/img/cancelfullscreen.png
C4iosCosmos/img/close.png
C4iosCosmos/img/fullscreen.png
C4iosCosmos/img/loader.gif
C4iosCosmos/img/menu-icon.png
C4iosCosmos/img/save.png
C4iosCosmos/img/saved.png
C4iosCosmos/img/settings-s.png
C4iosCosmos/img/settings.png
C4iosCosmos/img/star.png
C4iosCosmos/js/__init__.py
C4iosCosmos/js/epub.js
C4iosCosmos/js/epub.min.js
C4iosCosmos/js/epub.min.map
C4iosCosmos/js/hooks.min.js
C4iosCosmos/js/hooks.min.map
C4iosCosmos/js/reader.js
C4iosCosmos/js/reader.js.map
C4iosCosmos/js/reader.min.js
C4iosCosmos/js/reader.min.map
C4iosCosmos/js/hooks/__init__.py
C4iosCosmos/js/hooks/extensions/__init__.py
C4iosCosmos/js/hooks/extensions/highlight.js
C4iosCosmos/js/libs/__init__.py
C4iosCosmos/js/libs/jquery.min.js
C4iosCosmos/js/libs/localforage.min.js
C4iosCosmos/js/libs/screenfull.js
C4iosCosmos/js/libs/screenfull.min.js
C4iosCosmos/js/libs/zip.min.js
C4iosCosmos/js/plugins/__init__.py
C4iosCosmos/js/plugins/hypothesis.js
C4iosCosmos/js/plugins/search.js
c4ios_cosmos-2024.3.1.0.dist-info/METADATA
c4ios_cosmos-2024.3.1.0.dist-info/WHEEL
c4ios_cosmos-2024.3.1.0.dist-info/entry_points.txt
c4ios_cosmos-2024.3.1.0.dist-info/top_level.txt
c4ios_cosmos-2024.3.1.0.dist-info/RECORD
